Workbook

Sheet Inputs & Assumptions
A1: iPaaS Build vs. Buy — ROI Model: Inputs & Assumptions
A2: Yellow cells are placeholders — replace with your actual figures. Blue text = input cell, black = formula (do not edit).
A4: Engineering Cost Basis
A5: Blended loaded engineer rate ($/hour) | B5: 75 | C5: PLACEHOLDER — replace with your actual fully-loaded hourly cost (salary + benefits + overhead ÷ annual hours)
A6: Hours per engineer-week | B6: 40 | C6: Standard full-time week — adjust if your team runs differently
A8: Custom Build Effort Estimate
A9: Engineer-weeks already spent (POC Days 1–5) | B9: 6 | C9: PLACEHOLDER — replace with actual logged hours ÷ 40
A10: Engineer-weeks remaining to MVP (target Sep 1, 2026) | B10: 4 | C10: PLACEHOLDER — replace with your team's current estimate to complete
A11: Engineer-weeks per future provider adapter | B11: 2 | C11: PLACEHOLDER — ideally anchored to actual hours logged building the Keka adapter
A12: Projected new provider integrations over horizon | B12: 5 | C12: PLACEHOLDER — how many new source/target providers you expect to add
A13: Time horizon (years) | B13: 2 | C13: PLACEHOLDER — how far out this model should project
A15: Third-Party Tool Pricing
A16: Temporal Cloud monthly floor ($) | B16: 100 | C16: Source: Temporal Cloud pricing, Essentials plan floor (confirmed, from leadership brief research)
A17: Airbyte self-hosted infra, monthly ($, low) | B17: 500 | C17: Source: Airbyte self-hosted infra cost range (Integrate.io/Hevo pricing analysis, 2026)
A18: Airbyte self-hosted infra, monthly ($, high) | B18: 3000 | C18: Source: same
A19: Airbyte ops burden (fraction of 1 FTE) | B19: 0.1 | C19: Source: same — 'at least 0.1 FTE needed to maintain a production deployment'
A20: Nango paid tier (Cloud/Enterprise), annual | B20: Request quote | C20: Not publicly listed — sales-quoted. Excluded from the Nango total below until you have an actual number; do not present that total as complete.
A21: Workato annual cost ($, typical) | B21: 20000 | C21: Source: typical deal range $15k–25k/yr+ before scaling; midpoint used
A22: Boomi annual cost ($, estimate) | B22: 20000 | C22: Not publicly listed; research indicates comparable to or above Workato — PLACEHOLDER, request an actual quote
A23: Celigo monthly cost ($, typical) | B23: 3000 | C23: Source: $600–6,000/month range; midpoint used

Sheet ROI Calculation
A1: Total Cost of Ownership Over Horizon — Custom vs. Every Tool Considered
A2: Engineering cost is held equal across every option — every path still requires the same ConnectWise/Keka adapter work; only the tool/subscription layer differs. See Comments for what each row assumes.
A4: Option | B4: Engineering Cost ($) | C4: Tool / Subscription Cost ($) | D4: Total Cost ($) | E4: Extra Cost vs. Custom ($) | F4: Note
A5: Custom Build | B5: =('Inputs & Assumptions'!$B$9+'Inputs & Assumptions'!$B$10+'Inputs & Assumptions'!$B$11*'Inputs & Assumptions'!$B$12)*'Inputs & Assumptions'!$B$6*'Inputs & Assumptions'!$B$5 -> 60000 | C5: 0 | D5: =B5+C5 -> 60000 | E5: =D5-$D$5 -> 0 | F5: Baseline — no third-party subscription or ops layer
A6: Nango | B6: =('Inputs & Assumptions'!$B$9+'Inputs & Assumptions'!$B$10+'Inputs & Assumptions'!$B$11*'Inputs & Assumptions'!$B$12)*'Inputs & Assumptions'!$B$6*'Inputs & Assumptions'!$B$5 -> 60000 | C6: 0 | D6: =B6+C6 -> 60000 | E6: =D6-$D$5 -> 0 | F6: Free-tier engineering cost shown; Cloud/Enterprise tier is unpriced (see Inputs row 20) — actual total will be higher once quoted
A7: Temporal (Cloud) | B7: =('Inputs & Assumptions'!$B$9+'Inputs & Assumptions'!$B$10+'Inputs & Assumptions'!$B$11*'Inputs & Assumptions'!$B$12)*'Inputs & Assumptions'!$B$6*'Inputs & Assumptions'!$B$5 -> 60000 | C7: ='Inputs & Assumptions'!$B$16*12*'Inputs & Assumptions'!$B$13 -> 2400 | D7: =B7+C7 -> 62400 | E7: =D7-$D$5 -> 2400 | F7: Temporal Cloud monthly floor × 12 × horizon years
A8: Airbyte (self-hosted) | B8: =('Inputs & Assumptions'!$B$9+'Inputs & Assumptions'!$B$10+'Inputs & Assumptions'!$B$11*'Inputs & Assumptions'!$B$12)*'Inputs & Assumptions'!$B$6*'Inputs & Assumptions'!$B$5 -> 60000 | C8: =(('Inputs & Assumptions'!$B$17+'Inputs & Assumptions'!$B$18)/2)*12*'Inputs & Assumptions'!$B$13+'Inputs & Assumptions'!$B$19*('Inputs & Assumptions'!$B$6*52*'Inputs & Assumptions'!$B$13)*'Inputs & Assumptions'!$B$5 -> 73200 | D8: =B8+C8 -> 133200 | E8: =D8-$D$5 -> 73200 | F8: Midpoint infra cost + ops-FTE-fraction × engineer hours over horizon × blended rate
A9: Workato | B9: =('Inputs & Assumptions'!$B$9+'Inputs & Assumptions'!$B$10+'Inputs & Assumptions'!$B$11*'Inputs & Assumptions'!$B$12)*'Inputs & Assumptions'!$B$6*'Inputs & Assumptions'!$B$5 -> 60000 | C9: ='Inputs & Assumptions'!$B$21*'Inputs & Assumptions'!$B$13 -> 40000 | D9: =B9+C9 -> 100000 | E9: =D9-$D$5 -> 40000 | F9: Annual cost × horizon years
A10: Boomi | B10: =('Inputs & Assumptions'!$B$9+'Inputs & Assumptions'!$B$10+'Inputs & Assumptions'!$B$11*'Inputs & Assumptions'!$B$12)*'Inputs & Assumptions'!$B$6*'Inputs & Assumptions'!$B$5 -> 60000 | C10: ='Inputs & Assumptions'!$B$22*'Inputs & Assumptions'!$B$13 -> 40000 | D10: =B10+C10 -> 100000 | E10: =D10-$D$5 -> 40000 | F10: Annual cost (estimate) × horizon years
A11: Celigo | B11: =('Inputs & Assumptions'!$B$9+'Inputs & Assumptions'!$B$10+'Inputs & Assumptions'!$B$11*'Inputs & Assumptions'!$B$12)*'Inputs & Assumptions'!$B$6*'Inputs & Assumptions'!$B$5 -> 60000 | C11: ='Inputs & Assumptions'!$B$23*12*'Inputs & Assumptions'!$B$13 -> 72000 | D11: =B11+C11 -> 132000 | E11: =D11-$D$5 -> 72000 | F11: Monthly cost × 12 × horizon years
A13: Nango's total is understated until the Cloud/Enterprise quote (Inputs row 20) is added — treat it as a floor, not a final number. Boomi's annual cost is an estimate, not a published price — request an actual quote before presenting.

Sheet Summary
A1: ROI Summary
A2: Pulls directly from the ROI Calculation sheet — update the Inputs sheet, this refreshes automatically.
A4: Option | B4: Total Cost ($) | C4: Savings vs. Custom ($)
A5: ='ROI Calculation'!A5 -> Custom Build | B5: ='ROI Calculation'!D5 -> 60000 | C5: ='ROI Calculation'!E5 -> 0
A6: ='ROI Calculation'!A6 -> Nango | B6: ='ROI Calculation'!D6 -> 60000 | C6: ='ROI Calculation'!E6 -> 0
A7: ='ROI Calculation'!A7 -> Temporal (Cloud) | B7: ='ROI Calculation'!D7 -> 62400 | C7: ='ROI Calculation'!E7 -> 2400
A8: ='ROI Calculation'!A8 -> Airbyte (self-hosted) | B8: ='ROI Calculation'!D8 -> 133200 | C8: ='ROI Calculation'!E8 -> 73200
A9: ='ROI Calculation'!A9 -> Workato | B9: ='ROI Calculation'!D9 -> 100000 | C9: ='ROI Calculation'!E9 -> 40000
A10: ='ROI Calculation'!A10 -> Boomi | B10: ='ROI Calculation'!D10 -> 100000 | C10: ='ROI Calculation'!E10 -> 40000
A11: ='ROI Calculation'!A11 -> Celigo | B11: ='ROI Calculation'!D11 -> 132000 | C11: ='ROI Calculation'!E11 -> 72000
